README.rst
setup.py
async_task_processor/__init__.py
async_task_processor.egg-info/PKG-INFO
async_task_processor.egg-info/SOURCES.txt
async_task_processor.egg-info/dependency_links.txt
async_task_processor.egg-info/not-zip-safe
async_task_processor.egg-info/requires.txt
async_task_processor.egg-info/top_level.txt
async_task_processor/atp/__init__.py
async_task_processor/atp/atp.py
async_task_processor/exceptions/__init__.py
async_task_processor/primitives/__init__.py
async_task_processor/primitives/base_task.py
async_task_processor/primitives/tarantool_task.py
async_task_processor/primitives/task.py
async_task_processor/processors/__init__.py
async_task_processor/processors/base_processor.py
async_task_processor/processors/periodic_processor.py
async_task_processor/processors/simple_processor.py
async_task_processor/processors/tarantool_processor.py
examples/__init__.py
examples/periodic_processor.py
examples/tarantool_processor.py
examples/tarantool_processor_manage_workers.py