Metadata-Version: 1.0
Name: async-task-processor
Version: 0.2.6
Summary: Simple package to run async tasks
Home-page: https://github.com/moelius/async-task-processor
Author: Klimov Konstantin
Author-email: moelius1983@gmail.com
License: MIT
Platform: UNKNOWN
